pyframe/__init__.py
pyframe/cli.py
pyframe/compiler/__init__.py
pyframe/compiler/ast_transformer.py
pyframe/compiler/js_generator.py
pyframe/compiler/transpiler.py
pyframe/core/__init__.py
pyframe/core/app.py
pyframe/core/component.py
pyframe/core/routing.py
pyframe/data/__init__.py
pyframe/data/api_generator.py
pyframe/data/database.py
pyframe/data/migrations.py
pyframe/data/models.py
pyframe/plugins/__init__.py
pyframe/plugins/analytics_plugin.py
pyframe/plugins/auth_plugin.py
pyframe/plugins/cache_plugin.py
pyframe/plugins/hooks.py
pyframe/plugins/plugin.py
pyframe/realtime/__init__.py
pyframe/realtime/channels.py
pyframe/realtime/live_sync.py
pyframe/realtime/sse_manager.py
pyframe/realtime/websocket_manager.py
pyframe/server/__init__.py
pyframe/server/context.py
pyframe/server/dev_server.py
pyframe/server/simple_server.py
pyframe_web-0.1.0.dist-info/licenses/LICENSE
pyframe_web-0.1.0.dist-info/METADATA
pyframe_web-0.1.0.dist-info/WHEEL
pyframe_web-0.1.0.dist-info/entry_points.txt
pyframe_web-0.1.0.dist-info/top_level.txt
pyframe_web-0.1.0.dist-info/RECORD
