Metadata-Version: 2.4
Name: pyframe-web
Version: 0.1.0
Summary: Revolutionary Full-Stack Python Web Framework - Write React-like components in pure Python
Home-page: https://github.com/PyFrameWeb/PyFrame
Author: PyFrame Team
Author-email: PyFrame Team <pyframe@example.com>
License: MIT
Project-URL: Homepage, https://github.com/PyFrameWeb/PyFrame
Project-URL: Documentation, https://github.com/PyFrameWeb/PyFrame/blob/main/README.md
Project-URL: Repository, https://github.com/PyFrameWeb/PyFrame
Project-URL: Bug Tracker, https://github.com/PyFrameWeb/PyFrame/issues
Project-URL: Changelog, https://github.com/PyFrameWeb/PyFrame/blob/main/CHANGELOG.md
Keywords: web framework,python,react,components,frontend,backend,full-stack,reactive,hot-reload,transpiler,javascript
Classifier: Development Status :: 4 - Beta
Classifier: Intended Audience :: Developers
Classifier: License :: OSI Approved :: MIT License
Classifier: Operating System :: OS Independent
Classifier: Programming Language :: Python :: 3
Classifier: Programming Language :: Python :: 3.8
Classifier: Programming Language :: Python :: 3.9
Classifier: Programming Language :: Python :: 3.10
Classifier: Programming Language :: Python :: 3.11
Classifier: Programming Language :: Python :: 3.12
Classifier: Topic :: Internet :: WWW/HTTP :: Dynamic Content
Classifier: Topic :: Software Development :: Libraries :: Python Modules
Classifier: Topic :: Software Development :: User Interfaces
Classifier: Framework :: AsyncIO
Requires-Python: >=3.8
License-File: LICENSE
Requires-Dist: websockets>=11.0.0
Requires-Dist: watchdog>=3.0.0
Requires-Dist: aiofiles>=23.0.0
Requires-Dist: jinja2>=3.1.0
Requires-Dist: click>=8.0.0
Provides-Extra: dev
Requires-Dist: pytest>=7.0.0; extra == "dev"
Requires-Dist: pytest-asyncio>=0.21.0; extra == "dev"
Requires-Dist: black>=23.0.0; extra == "dev"
Requires-Dist: flake8>=6.0.0; extra == "dev"
Requires-Dist: mypy>=1.0.0; extra == "dev"
Requires-Dist: pre-commit>=3.0.0; extra == "dev"
Provides-Extra: database
Requires-Dist: sqlalchemy>=2.0.0; extra == "database"
Requires-Dist: alembic>=1.12.0; extra == "database"
Provides-Extra: cache
Requires-Dist: redis>=4.5.0; extra == "cache"
Requires-Dist: memcached>=1.6.0; extra == "cache"
Provides-Extra: all
Requires-Dist: pyframe[cache,database,dev]; extra == "all"
Dynamic: author
Dynamic: home-page
Dynamic: license-file
Dynamic: requires-python
